{
  "SPDXID" : "SPDXRef-DOCUMENT",
  "spdxVersion" : "SPDX-2.3",
  "creationInfo" : {
    "comment" : "Converted from CycloneDX spec version 1.4",
    "created" : "2023-08-20T08:22:43Z",
    "creators" : [ "Tool: CycloneDX:cyclonedx-bom-3.11.2", "Tool: CycloneDX:cyclonedx-python-lib-3.1.5", "Tool: CycloneToSpdx-0.1.4" ],
    "licenseListVersion" : "3.21"
  },
  "name" : "From-Cyclone-DX",
  "dataLicense" : "CC0-1.0",
  "annotations" : [ {
    "annotationDate" : "2023-08-20T08:22:44Z",
    "annotationType" : "OTHER",
    "annotator" : "Tool: CycloneToSpdx",
    "comment" : "MISSING_CDX_PROPERTY:extensions={}"
  } ],
  "documentNamespace" : "https://cyclonedx/b1b8c747-72f3-4aed-9c89-263b73cfcd93_1",
  "packages" : [ {
    "SPDXID" : "SPDXRef-3ad986ab-4123-4dfb-be80-b74f5583697d",
    "annotations" : [ {
      "annotationDate" : "2023-08-20T08:22:44Z",
      "annotationType" : "OTHER",
      "annotator" : "Tool: CycloneToSpdx",
      "comment" : "MISSING_CDX_PROPERTY:componentType=\"LIBRARY\""
    } ],
    "copyrightText" : "NOASSERTION",
    "downloadLocation" : "NOASSERTION",
    "externalRefs" : [ {
      "referenceCategory" : "PACKAGE-MANAGER",
      "referenceLocator" : "pkg:pypi/referencing@0.30.2",
      "referenceType" : "purl"
    } ],
    "filesAnalyzed" : false,
    "licenseConcluded" : "NOASSERTION",
    "licenseDeclared" : "NOASSERTION",
    "name" : "referencing",
    "primaryPackagePurpose" : "LIBRARY",
    "versionInfo" : "0.30.2"
  }, {
    "SPDXID" : "SPDXRef-d75961c3-6711-4ea6-8c72-87c8edc86509",
    "annotations" : [ {
      "annotationDate" : "2023-08-20T08:22:44Z",
      "annotationType" : "OTHER",
      "annotator" : "Tool: CycloneToSpdx",
      "comment" : "MISSING_CDX_PROPERTY:componentType=\"LIBRARY\""
    } ],
    "copyrightText" : "NOASSERTION",
    "downloadLocation" : "NOASSERTION",
    "externalRefs" : [ {
      "referenceCategory" : "PACKAGE-MANAGER",
      "referenceLocator" : "pkg:pypi/pyyaml@6.0.1",
      "referenceType" : "purl"
    } ],
    "filesAnalyzed" : false,
    "licenseConcluded" : "NOASSERTION",
    "licenseDeclared" : "NOASSERTION",
    "name" : "PyYAML",
    "primaryPackagePurpose" : "LIBRARY",
    "versionInfo" : "6.0.1"
  }, {
    "SPDXID" : "SPDXRef-39743171-83c6-4c4f-b343-e392f2ca263b",
    "annotations" : [ {
      "annotationDate" : "2023-08-20T08:22:44Z",
      "annotationType" : "OTHER",
      "annotator" : "Tool: CycloneToSpdx",
      "comment" : "MISSING_CDX_PROPERTY:componentType=\"LIBRARY\""
    } ],
    "copyrightText" : "NOASSERTION",
    "downloadLocation" : "NOASSERTION",
    "externalRefs" : [ {
      "referenceCategory" : "PACKAGE-MANAGER",
      "referenceLocator" : "pkg:pypi/jsonschema@4.19.0",
      "referenceType" : "purl"
    } ],
    "filesAnalyzed" : false,
    "licenseConcluded" : "NOASSERTION",
    "licenseDeclared" : "NOASSERTION",
    "name" : "jsonschema",
    "primaryPackagePurpose" : "LIBRARY",
    "versionInfo" : "4.19.0"
  }, {
    "SPDXID" : "SPDXRef-ee2299d5-4211-4a6e-9386-5a6353f5a474",
    "annotations" : [ {
      "annotationDate" : "2023-08-20T08:22:44Z",
      "annotationType" : "OTHER",
      "annotator" : "Tool: CycloneToSpdx",
      "comment" : "MISSING_CDX_PROPERTY:componentType=\"LIBRARY\""
    } ],
    "copyrightText" : "NOASSERTION",
    "downloadLocation" : "NOASSERTION",
    "externalRefs" : [ {
      "referenceCategory" : "PACKAGE-MANAGER",
      "referenceLocator" : "pkg:pypi/typer@0.9.0",
      "referenceType" : "purl"
    } ],
    "filesAnalyzed" : false,
    "licenseConcluded" : "NOASSERTION",
    "licenseDeclared" : "NOASSERTION",
    "name" : "typer",
    "primaryPackagePurpose" : "LIBRARY",
    "versionInfo" : "0.9.0"
  }, {
    "SPDXID" : "SPDXRef-92ebf3d7-9fa4-4a51-9e9a-91d8ae96000b",
    "annotations" : [ {
      "annotationDate" : "2023-08-20T08:22:44Z",
      "annotationType" : "OTHER",
      "annotator" : "Tool: CycloneToSpdx",
      "comment" : "MISSING_CDX_PROPERTY:componentType=\"LIBRARY\""
    } ],
    "copyrightText" : "NOASSERTION",
    "downloadLocation" : "NOASSERTION",
    "externalRefs" : [ {
      "referenceCategory" : "PACKAGE-MANAGER",
      "referenceLocator" : "pkg:pypi/first@2.0.2",
      "referenceType" : "purl"
    } ],
    "filesAnalyzed" : false,
    "licenseConcluded" : "NOASSERTION",
    "licenseDeclared" : "NOASSERTION",
    "name" : "first",
    "primaryPackagePurpose" : "LIBRARY",
    "versionInfo" : "2.0.2"
  }, {
    "SPDXID" : "SPDXRef-f3466a4f-b46c-449d-8841-a06f5eea5b15",
    "annotations" : [ {
      "annotationDate" : "2023-08-20T08:22:44Z",
      "annotationType" : "OTHER",
      "annotator" : "Tool: CycloneToSpdx",
      "comment" : "MISSING_CDX_PROPERTY:componentType=\"LIBRARY\""
    } ],
    "copyrightText" : "NOASSERTION",
    "downloadLocation" : "NOASSERTION",
    "externalRefs" : [ {
      "referenceCategory" : "PACKAGE-MANAGER",
      "referenceLocator" : "pkg:pypi/lxml@4.9.3",
      "referenceType" : "purl"
    } ],
    "filesAnalyzed" : false,
    "licenseConcluded" : "NOASSERTION",
    "licenseDeclared" : "NOASSERTION",
    "name" : "lxml",
    "primaryPackagePurpose" : "LIBRARY",
    "versionInfo" : "4.9.3"
  }, {
    "SPDXID" : "SPDXRef-e6c54913-30d4-4839-84e8-27ef31075e10",
    "annotations" : [ {
      "annotationDate" : "2023-08-20T08:22:44Z",
      "annotationType" : "OTHER",
      "annotator" : "Tool: CycloneToSpdx",
      "comment" : "MISSING_CDX_PROPERTY:componentType=\"LIBRARY\""
    } ],
    "copyrightText" : "NOASSERTION",
    "downloadLocation" : "NOASSERTION",
    "externalRefs" : [ {
      "referenceCategory" : "PACKAGE-MANAGER",
      "referenceLocator" : "pkg:pypi/msgspec@0.18.1",
      "referenceType" : "purl"
    } ],
    "filesAnalyzed" : false,
    "licenseConcluded" : "NOASSERTION",
    "licenseDeclared" : "NOASSERTION",
    "name" : "msgspec",
    "primaryPackagePurpose" : "LIBRARY",
    "versionInfo" : "0.18.1"
  }, {
    "SPDXID" : "SPDXRef-4dce8be7-3bcf-49a9-92d5-566d665d479e",
    "annotations" : [ {
      "annotationDate" : "2023-08-20T08:22:44Z",
      "annotationType" : "OTHER",
      "annotator" : "Tool: CycloneToSpdx",
      "comment" : "MISSING_CDX_PROPERTY:componentType=\"LIBRARY\""
    } ],
    "copyrightText" : "NOASSERTION",
    "downloadLocation" : "NOASSERTION",
    "externalRefs" : [ {
      "referenceCategory" : "PACKAGE-MANAGER",
      "referenceLocator" : "pkg:pypi/kdl-py@1.1.0",
      "referenceType" : "purl"
    } ],
    "filesAnalyzed" : false,
    "licenseConcluded" : "NOASSERTION",
    "licenseDeclared" : "NOASSERTION",
    "name" : "kdl-py",
    "primaryPackagePurpose" : "LIBRARY",
    "versionInfo" : "1.1.0"
  }, {
    "SPDXID" : "SPDXRef-435cacb4-848d-40eb-83ce-7ffd1c584e23",
    "annotations" : [ {
      "annotationDate" : "2023-08-20T08:22:44Z",
      "annotationType" : "OTHER",
      "annotator" : "Tool: CycloneToSpdx",
      "comment" : "MISSING_CDX_PROPERTY:componentType=\"LIBRARY\""
    } ],
    "copyrightText" : "NOASSERTION",
    "downloadLocation" : "NOASSERTION",
    "externalRefs" : [ {
      "referenceCategory" : "PACKAGE-MANAGER",
      "referenceLocator" : "pkg:pypi/toml@0.10.2",
      "referenceType" : "purl"
    } ],
    "filesAnalyzed" : false,
    "licenseConcluded" : "NOASSERTION",
    "licenseDeclared" : "NOASSERTION",
    "name" : "toml",
    "primaryPackagePurpose" : "LIBRARY",
    "versionInfo" : "0.10.2"
  }, {
    "SPDXID" : "SPDXRef-9892df5b-0995-4a61-9201-55cae1b5f0d5",
    "annotations" : [ {
      "annotationDate" : "2023-08-20T08:22:44Z",
      "annotationType" : "OTHER",
      "annotator" : "Tool: CycloneToSpdx",
      "comment" : "MISSING_CDX_PROPERTY:componentType=\"LIBRARY\""
    } ],
    "copyrightText" : "NOASSERTION",
    "downloadLocation" : "NOASSERTION",
    "externalRefs" : [ {
      "referenceCategory" : "PACKAGE-MANAGER",
      "referenceLocator" : "pkg:pypi/xmlschema@2.4.0",
      "referenceType" : "purl"
    } ],
    "filesAnalyzed" : false,
    "licenseConcluded" : "NOASSERTION",
    "licenseDeclared" : "NOASSERTION",
    "name" : "xmlschema",
    "primaryPackagePurpose" : "LIBRARY",
    "versionInfo" : "2.4.0"
  }, {
    "SPDXID" : "SPDXRef-834326e1-15d4-47ec-9efc-11738dba166c",
    "annotations" : [ {
      "annotationDate" : "2023-08-20T08:22:44Z",
      "annotationType" : "OTHER",
      "annotator" : "Tool: CycloneToSpdx",
      "comment" : "MISSING_CDX_PROPERTY:componentType=\"LIBRARY\""
    } ],
    "copyrightText" : "NOASSERTION",
    "downloadLocation" : "NOASSERTION",
    "externalRefs" : [ {
      "referenceCategory" : "PACKAGE-MANAGER",
      "referenceLocator" : "pkg:pypi/jmespath@1.0.1",
      "referenceType" : "purl"
    } ],
    "filesAnalyzed" : false,
    "licenseConcluded" : "NOASSERTION",
    "licenseDeclared" : "NOASSERTION",
    "name" : "jmespath",
    "primaryPackagePurpose" : "LIBRARY",
    "versionInfo" : "1.0.1"
  } ],
  "relationships" : [ {
    "spdxElementId" : "SPDXRef-DOCUMENT",
    "relationshipType" : "DESCRIBES",
    "relatedSpdxElement" : "SPDXRef-834326e1-15d4-47ec-9efc-11738dba166c"
  }, {
    "spdxElementId" : "SPDXRef-DOCUMENT",
    "relationshipType" : "DESCRIBES",
    "relatedSpdxElement" : "SPDXRef-92ebf3d7-9fa4-4a51-9e9a-91d8ae96000b"
  }, {
    "spdxElementId" : "SPDXRef-DOCUMENT",
    "relationshipType" : "DESCRIBES",
    "relatedSpdxElement" : "SPDXRef-ee2299d5-4211-4a6e-9386-5a6353f5a474"
  }, {
    "spdxElementId" : "SPDXRef-DOCUMENT",
    "relationshipType" : "DESCRIBES",
    "relatedSpdxElement" : "SPDXRef-435cacb4-848d-40eb-83ce-7ffd1c584e23"
  }, {
    "spdxElementId" : "SPDXRef-DOCUMENT",
    "relationshipType" : "DESCRIBES",
    "relatedSpdxElement" : "SPDXRef-d75961c3-6711-4ea6-8c72-87c8edc86509"
  }, {
    "spdxElementId" : "SPDXRef-DOCUMENT",
    "relationshipType" : "DESCRIBES",
    "relatedSpdxElement" : "SPDXRef-9892df5b-0995-4a61-9201-55cae1b5f0d5"
  }, {
    "spdxElementId" : "SPDXRef-DOCUMENT",
    "relationshipType" : "DESCRIBES",
    "relatedSpdxElement" : "SPDXRef-f3466a4f-b46c-449d-8841-a06f5eea5b15"
  }, {
    "spdxElementId" : "SPDXRef-DOCUMENT",
    "relationshipType" : "DESCRIBES",
    "relatedSpdxElement" : "SPDXRef-4dce8be7-3bcf-49a9-92d5-566d665d479e"
  }, {
    "spdxElementId" : "SPDXRef-DOCUMENT",
    "relationshipType" : "DESCRIBES",
    "relatedSpdxElement" : "SPDXRef-3ad986ab-4123-4dfb-be80-b74f5583697d"
  }, {
    "spdxElementId" : "SPDXRef-DOCUMENT",
    "relationshipType" : "DESCRIBES",
    "relatedSpdxElement" : "SPDXRef-e6c54913-30d4-4839-84e8-27ef31075e10"
  }, {
    "spdxElementId" : "SPDXRef-DOCUMENT",
    "relationshipType" : "DESCRIBES",
    "relatedSpdxElement" : "SPDXRef-39743171-83c6-4c4f-b343-e392f2ca263b"
  } ]
}